date_calculator/__init__.py
date_calculator/core.py
date_calculator-0.1.1.dist-info/LICENSE
date_calculator-0.1.1.dist-info/METADATA
date_calculator-0.1.1.dist-info/WHEEL
date_calculator-0.1.1.dist-info/top_level.txt
date_calculator-0.1.1.dist-info/RECORD
